papyrus_ogcproxy/__init__.py
papyrus_ogcproxy/views.py
papyrus_ogcproxy-0.2.dist-info/DESCRIPTION.rst
papyrus_ogcproxy-0.2.dist-info/METADATA
papyrus_ogcproxy-0.2.dist-info/RECORD
papyrus_ogcproxy-0.2.dist-info/WHEEL
papyrus_ogcproxy-0.2.dist-info/entry_points.txt
papyrus_ogcproxy-0.2.dist-info/metadata.json
papyrus_ogcproxy-0.2.dist-info/paster_plugins.txt
papyrus_ogcproxy-0.2.dist-info/top_level.txt
