Metadata-Version: 2.0
Name: papyrus-ogcproxy
Version: 0.2
Summary: papyrus_ogcproxy
Home-page: http://github.com/elemoine/papyrus_ogcproxy
Author: Eric Lemoine
Author-email: eric.lemoine@gmail.com
License: UNKNOWN
Keywords: web geospatial papyrus OGC pyramid pylons
Platform: UNKNOWN
Classifier: Programming Language :: Python
Classifier: Framework :: Pylons
Classifier: Topic :: Internet :: WWW/HTTP
Classifier: Topic :: Internet :: WWW/HTTP :: WSGI :: Application
Requires-Dist: WebError
Requires-Dist: httplib2
Requires-Dist: pyramid
